pySSHA/__init__.py
pySSHA/ssha.py
pySSHA/test.py
pySSHA-1.0.0.data/scripts/ssha.py
pySSHA-1.0.0.dist-info/METADATA
pySSHA-1.0.0.dist-info/RECORD
pySSHA-1.0.0.dist-info/WHEEL
pySSHA-1.0.0.dist-info/top_level.txt
